{
  "metadata": {
    "toolPackage": "@microsoft/api-extractor",
    "toolVersion": "7.42.3",
    "schemaVersion": 1011,
    "oldestForwardsCompatibleVersion": 1001,
    "tsdocConfig": {
      "$schema": "https://developer.microsoft.com/json-schemas/tsdoc/v0/tsdoc.schema.json",
      "noStandardTags": true,
      "tagDefinitions": [
        {
          "tagName": "@alpha",
          "syntaxKind": "modifier"
        },
        {
          "tagName": "@beta",
          "syntaxKind": "modifier"
        },
        {
          "tagName": "@defaultValue",
          "syntaxKind": "block"
        },
        {
          "tagName": "@decorator",
          "syntaxKind": "block",
          "allowMultiple": true
        },
        {
          "tagName": "@deprecated",
          "syntaxKind": "block"
        },
        {
          "tagName": "@eventProperty",
          "syntaxKind": "modifier"
        },
        {
          "tagName": "@example",
          "syntaxKind": "block",
          "allowMultiple": true
        },
        {
          "tagName": "@experimental",
          "syntaxKind": "modifier"
        },
        {
          "tagName": "@inheritDoc",
          "syntaxKind": "inline"
        },
        {
          "tagName": "@internal",
          "syntaxKind": "modifier"
        },
        {
          "tagName": "@label",
          "syntaxKind": "inline"
        },
        {
          "tagName": "@link",
          "syntaxKind": "inline",
          "allowMultiple": true
        },
        {
          "tagName": "@override",
          "syntaxKind": "modifier"
        },
        {
          "tagName": "@packageDocumentation",
          "syntaxKind": "modifier"
        },
        {
          "tagName": "@param",
          "syntaxKind": "block",
          "allowMultiple": true
        },
        {
          "tagName": "@privateRemarks",
          "syntaxKind": "block"
        },
        {
          "tagName": "@public",
          "syntaxKind": "modifier"
        },
        {
          "tagName": "@readonly",
          "syntaxKind": "modifier"
        },
        {
          "tagName": "@remarks",
          "syntaxKind": "block"
        },
        {
          "tagName": "@returns",
          "syntaxKind": "block"
        },
        {
          "tagName": "@sealed",
          "syntaxKind": "modifier"
        },
        {
          "tagName": "@see",
          "syntaxKind": "block"
        },
        {
          "tagName": "@throws",
          "syntaxKind": "block",
          "allowMultiple": true
        },
        {
          "tagName": "@typeParam",
          "syntaxKind": "block",
          "allowMultiple": true
        },
        {
          "tagName": "@virtual",
          "syntaxKind": "modifier"
        },
        {
          "tagName": "@Author",
          "syntaxKind": "block"
        },
        {
          "tagName": "@Date",
          "syntaxKind": "block"
        },
        {
          "tagName": "@LastEditors",
          "syntaxKind": "block"
        },
        {
          "tagName": "@LastEditTime",
          "syntaxKind": "block"
        },
        {
          "tagName": "@Description",
          "syntaxKind": "block"
        }
      ],
      "reportUnsupportedHtmlElements": false
    }
  },
  "kind": "Package",
  "canonicalReference": "@hz-9/a4-docs!",
  "docComment": "",
  "name": "@hz-9/a4-docs",
  "preserveMemberOrder": false,
  "members": [
    {
      "kind": "EntryPoint",
      "canonicalReference": "@hz-9/a4-docs!",
      "name": "",
      "preserveMemberOrder": false,
      "members": [
        {
          "kind": "Class",
          "canonicalReference": "@hz-9/a4-docs!A4Docs:class",
          "docComment": "/**\n * `A4 Docs` 核心服务类。\n *\n * @public\n */\n",
          "excerptTokens": [
            {
              "kind": "Content",
              "text": "export declare class A4Docs implements "
            },
            {
              "kind": "Reference",
              "text": "IA4Docs",
              "canonicalReference": "@hz-9/a4-core!IA4Docs:class"
            },
            {
              "kind": "Content",
              "text": " "
            }
          ],
          "fileUrlPath": "dist/module/docs.d.ts",
          "releaseTag": "Public",
          "isAbstract": false,
          "name": "A4Docs",
          "preserveMemberOrder": false,
          "members": [
            {
              "kind": "Constructor",
              "canonicalReference": "@hz-9/a4-docs!A4Docs:constructor(1)",
              "docComment": "/**\n * Constructs a new instance of the `A4Docs` class\n */\n",
              "excerptTokens": [
                {
                  "kind": "Content",
                  "text": "constructor(options: "
                },
                {
                  "kind": "Reference",
                  "text": "IDocsConstructorOptions",
                  "canonicalReference": "@hz-9/a4-docs!IDocsConstructorOptions:interface"
                },
                {
                  "kind": "Content",
                  "text": ");"
                }
              ],
              "releaseTag": "Public",
              "isProtected": false,
              "overloadIndex": 1,
              "parameters": [
                {
                  "parameterName": "options",
                  "parameterTypeTokenRange": {
                    "startIndex": 1,
                    "endIndex": 2
                  },
                  "isOptional": false
                }
              ]
            },
            {
              "kind": "Method",
              "canonicalReference": "@hz-9/a4-docs!A4Docs#getHomePageHtml:member(1)",
              "docComment": "",
              "excerptTokens": [
                {
                  "kind": "Content",
                  "text": "getHomePageHtml(): "
                },
                {
                  "kind": "Content",
                  "text": "string"
                },
                {
                  "kind": "Content",
                  "text": ";"
                }
              ],
              "isStatic": false,
              "returnTypeTokenRange": {
                "startIndex": 1,
                "endIndex": 2
              },
              "releaseTag": "Public",
              "isProtected": false,
              "overloadIndex": 1,
              "parameters": [],
              "isOptional": false,
              "isAbstract": false,
              "name": "getHomePageHtml"
            },
            {
              "kind": "Property",
              "canonicalReference": "@hz-9/a4-docs!A4Docs#homeLinkOptions:member",
              "docComment": "",
              "excerptTokens": [
                {
                  "kind": "Content",
                  "text": "protected readonly homeLinkOptions: "
                },
                {
                  "kind": "Reference",
                  "text": "IHomeLinkOption",
                  "canonicalReference": "@hz-9/a4-docs!~IHomeLinkOption:interface"
                },
                {
                  "kind": "Content",
                  "text": "[]"
                },
                {
                  "kind": "Content",
                  "text": ";"
                }
              ],
              "isReadonly": true,
              "isOptional": false,
              "releaseTag": "Public",
              "name": "homeLinkOptions",
              "propertyTypeTokenRange": {
                "startIndex": 1,
                "endIndex": 3
              },
              "isStatic": false,
              "isProtected": true,
              "isAbstract": false
            },
            {
              "kind": "Method",
              "canonicalReference": "@hz-9/a4-docs!A4Docs#init:member(1)",
              "docComment": "/**\n * 初始化\n *\n * @public\n */\n",
              "excerptTokens": [
                {
                  "kind": "Content",
                  "text": "init(app: "
                },
                {
                  "kind": "Reference",
                  "text": "A4Application",
                  "canonicalReference": "@hz-9/a4-core!A4Application:class"
                },
                {
                  "kind": "Content",
                  "text": "): "
                },
                {
                  "kind": "Reference",
                  "text": "Promise",
                  "canonicalReference": "!Promise:interface"
                },
                {
                  "kind": "Content",
                  "text": "<void>"
                },
                {
                  "kind": "Content",
                  "text": ";"
                }
              ],
              "isStatic": false,
              "returnTypeTokenRange": {
                "startIndex": 3,
                "endIndex": 5
              },
              "releaseTag": "Public",
              "isProtected": false,
              "overloadIndex": 1,
              "parameters": [
                {
                  "parameterName": "app",
                  "parameterTypeTokenRange": {
                    "startIndex": 1,
                    "endIndex": 2
                  },
                  "isOptional": false
                }
              ],
              "isOptional": false,
              "isAbstract": false,
              "name": "init"
            },
            {
              "kind": "Property",
              "canonicalReference": "@hz-9/a4-docs!A4Docs#logger:member",
              "docComment": "",
              "excerptTokens": [
                {
                  "kind": "Content",
                  "text": "protected readonly logger: "
                },
                {
                  "kind": "Reference",
                  "text": "Logger",
                  "canonicalReference": "@nestjs/common!Logger:class"
                },
                {
                  "kind": "Content",
                  "text": ";"
                }
              ],
              "isReadonly": true,
              "isOptional": false,
              "releaseTag": "Public",
              "name": "logger",
              "propertyTypeTokenRange": {
                "startIndex": 1,
                "endIndex": 2
              },
              "isStatic": false,
              "isProtected": true,
              "isAbstract": false
            },
            {
              "kind": "Property",
              "canonicalReference": "@hz-9/a4-docs!A4Docs#options:member",
              "docComment": "",
              "excerptTokens": [
                {
                  "kind": "Content",
                  "text": "protected readonly options: "
                },
                {
                  "kind": "Reference",
                  "text": "IDocsConstructorOptions",
                  "canonicalReference": "@hz-9/a4-docs!IDocsConstructorOptions:interface"
                },
                {
                  "kind": "Content",
                  "text": ";"
                }
              ],
              "isReadonly": true,
              "isOptional": false,
              "releaseTag": "Public",
              "name": "options",
              "propertyTypeTokenRange": {
                "startIndex": 1,
                "endIndex": 2
              },
              "isStatic": false,
              "isProtected": true,
              "isAbstract": false
            }
          ],
          "implementsTokenRanges": [
            {
              "startIndex": 1,
              "endIndex": 2
            }
          ]
        },
        {
          "kind": "Class",
          "canonicalReference": "@hz-9/a4-docs!A4DocsFileModuleSchema:class",
          "docComment": "/**\n * `A4 Docs Module` 的配置项结构。(.file)\n *\n * @public\n */\n",
          "excerptTokens": [
            {
              "kind": "Content",
              "text": "export declare class A4DocsFileModuleSchema "
            }
          ],
          "fileUrlPath": "dist/schema/docs.schema.d.ts",
          "releaseTag": "Public",
          "isAbstract": false,
          "name": "A4DocsFileModuleSchema",
          "preserveMemberOrder": false,
          "members": [
            {
              "kind": "Property",
              "canonicalReference": "@hz-9/a4-docs!A4DocsFileModuleSchema#export:member",
              "docComment": "/**\n * 是否导出 json 文件。\n *\n * 作为 `ConfitSchema` 时，若缺省，则赋值为 [DOCS_MODULE_DEFAULT.SINGLE_FILE.EXPORT]\n */\n",
              "excerptTokens": [
                {
                  "kind": "Content",
                  "text": "readonly export: "
                },
                {
                  "kind": "Content",
                  "text": "boolean"
                },
                {
                  "kind": "Content",
                  "text": ";"
                }
              ],
              "isReadonly": true,
              "isOptional": false,
              "releaseTag": "Public",
              "name": "export",
              "propertyTypeTokenRange": {
                "startIndex": 1,
                "endIndex": 2
              },
              "isStatic": false,
              "isProtected": false,
              "isAbstract": false
            },
            {
              "kind": "Property",
              "canonicalReference": "@hz-9/a4-docs!A4DocsFileModuleSchema#filedir:member",
              "docComment": "/**\n * `Swagger` json 文件存储路径。\n *\n * 作为 `ConfitSchema` 时，若缺省，则赋值为 [DOCS_MODULE_DEFAULT.SINGLE_FILE.FILEDIR]\n */\n",
              "excerptTokens": [
                {
                  "kind": "Content",
                  "text": "readonly filedir: "
                },
                {
                  "kind": "Content",
                  "text": "string"
                },
                {
                  "kind": "Content",
                  "text": ";"
                }
              ],
              "isReadonly": true,
              "isOptional": false,
              "releaseTag": "Public",
              "name": "filedir",
              "propertyTypeTokenRange": {
                "startIndex": 1,
                "endIndex": 2
              },
              "isStatic": false,
              "isProtected": false,
              "isAbstract": false
            },
            {
              "kind": "Property",
              "canonicalReference": "@hz-9/a4-docs!A4DocsFileModuleSchema#filename:member",
              "docComment": "/**\n * `Swagger` json 格式信息访问地址。\n *\n * 作为 `ConfitSchema` 时，若缺省，则赋值为 [DOCS_MODULE_DEFAULT.SINGLE_FILE.FILENAME]\n *\n * 若服务启动地址为 `http://127.0.0.1:8080`， 则 `http://127.0.0.1:8080/${PREFIX}/${FILENAME}`（默认为 'http://127.0.0.1:8080/docs/'openapi.single.json''） 地址访问所有 `Swagger` 在线文档。\n */\n",
              "excerptTokens": [
                {
                  "kind": "Content",
                  "text": "readonly filename: "
                },
                {
                  "kind": "Content",
                  "text": "string"
                },
                {
                  "kind": "Content",
                  "text": ";"
                }
              ],
              "isReadonly": true,
              "isOptional": false,
              "releaseTag": "Public",
              "name": "filename",
              "propertyTypeTokenRange": {
                "startIndex": 1,
                "endIndex": 2
              },
              "isStatic": false,
              "isProtected": false,
              "isAbstract": false
            },
            {
              "kind": "Property",
              "canonicalReference": "@hz-9/a4-docs!A4DocsFileModuleSchema#open:member",
              "docComment": "/**\n * 是否显示 `Swagger` 在线文档。\n *\n * 作为 `ConfitSchema` 时，若缺省，则赋值为 [DOCS_MODULE_DEFAULT.SINGLE_FILE.OPEN]\n */\n",
              "excerptTokens": [
                {
                  "kind": "Content",
                  "text": "readonly open: "
                },
                {
                  "kind": "Content",
                  "text": "boolean"
                },
                {
                  "kind": "Content",
                  "text": ";"
                }
              ],
              "isReadonly": true,
              "isOptional": false,
              "releaseTag": "Public",
              "name": "open",
              "propertyTypeTokenRange": {
                "startIndex": 1,
                "endIndex": 2
              },
              "isStatic": false,
              "isProtected": false,
              "isAbstract": false
            }
          ],
          "implementsTokenRanges": []
        },
        {
          "kind": "Class",
          "canonicalReference": "@hz-9/a4-docs!A4DocsModule:class",
          "docComment": "/**\n * `A4 Docs` 核心模块类。\n *\n * @public\n */\n",
          "excerptTokens": [
            {
              "kind": "Content",
              "text": "export declare class A4DocsModule extends "
            },
            {
              "kind": "Reference",
              "text": "A4DocsModuleBase",
              "canonicalReference": "@hz-9/a4-docs!~A4DocsModuleBase"
            },
            {
              "kind": "Content",
              "text": " "
            }
          ],
          "fileUrlPath": "dist/module/docs.module.d.ts",
          "releaseTag": "Public",
          "isAbstract": false,
          "name": "A4DocsModule",
          "preserveMemberOrder": false,
          "members": [
            {
              "kind": "Method",
              "canonicalReference": "@hz-9/a4-docs!A4DocsModule.configToOptions:member(1)",
              "docComment": "",
              "excerptTokens": [
                {
                  "kind": "Content",
                  "text": "static configToOptions(config: "
                },
                {
                  "kind": "Reference",
                  "text": "A4DocsModuleSchema",
                  "canonicalReference": "@hz-9/a4-docs!A4DocsModuleSchema:class"
                },
                {
                  "kind": "Content",
                  "text": ", a4Config?: "
                },
                {
                  "kind": "Reference",
                  "text": "IA4Config",
                  "canonicalReference": "@hz-9/a4-core!IA4Config:class"
                },
                {
                  "kind": "Content",
                  "text": "<"
                },
                {
                  "kind": "Reference",
                  "text": "A4DocsModuleSchemaA",
                  "canonicalReference": "@hz-9/a4-docs!A4DocsModuleSchemaA:class"
                },
                {
                  "kind": "Content",
                  "text": ">"
                },
                {
                  "kind": "Content",
                  "text": "): "
                },
                {
                  "kind": "Reference",
                  "text": "IDocsInfo",
                  "canonicalReference": "@hz-9/a4-docs!IDocsInfo:interface"
                },
                {
                  "kind": "Content",
                  "text": ";"
                }
              ],
              "isStatic": true,
              "returnTypeTokenRange": {
                "startIndex": 8,
                "endIndex": 9
              },
              "releaseTag": "Public",
              "isProtected": false,
              "overloadIndex": 1,
              "parameters": [
                {
                  "parameterName": "config",
                  "parameterTypeTokenRange": {
                    "startIndex": 1,
                    "endIndex": 2
                  },
                  "isOptional": false
                },
                {
                  "parameterName": "a4Config",
                  "parameterTypeTokenRange": {
                    "startIndex": 3,
                    "endIndex": 7
                  },
                  "isOptional": true
                }
              ],
              "isOptional": false,
              "isAbstract": false,
              "name": "configToOptions"
            }
          ],
          "extendsTokenRange": {
            "startIndex": 1,
            "endIndex": 2
          },
          "implementsTokenRanges": []
        },
        {
          "kind": "Class",
          "canonicalReference": "@hz-9/a4-docs!A4DocsModuleSchema:class",
          "docComment": "/**\n * `A4 Docs Module` 的配置项结构。\n *\n * @public\n */\n",
          "excerptTokens": [
            {
              "kind": "Content",
              "text": "export declare class A4DocsModuleSchema "
            }
          ],
          "fileUrlPath": "dist/schema/docs.schema.d.ts",
          "releaseTag": "Public",
          "isAbstract": false,
          "name": "A4DocsModuleSchema",
          "preserveMemberOrder": false,
          "members": [
            {
              "kind": "Property",
              "canonicalReference": "@hz-9/a4-docs!A4DocsModuleSchema#file:member",
              "docComment": "",
              "excerptTokens": [
                {
                  "kind": "Content",
                  "text": "readonly file: "
                },
                {
                  "kind": "Reference",
                  "text": "A4DocsFileModuleSchema",
                  "canonicalReference": "@hz-9/a4-docs!A4DocsFileModuleSchema:class"
                },
                {
                  "kind": "Content",
                  "text": ";"
                }
              ],
              "isReadonly": true,
              "isOptional": false,
              "releaseTag": "Public",
              "name": "file",
              "propertyTypeTokenRange": {
                "startIndex": 1,
                "endIndex": 2
              },
              "isStatic": false,
              "isProtected": false,
              "isAbstract": false
            },
            {
              "kind": "Property",
              "canonicalReference": "@hz-9/a4-docs!A4DocsModuleSchema#prefix:member",
              "docComment": "/**\n * `A4 Docs` 所有接口的前缀。\n *\n * 作为 `ConfitSchema` 时，若缺省，则赋值为 [DOCS_MODULE_DEFAULT.PREFIX]\n *\n * 若服务启动地址为 `http://127.0.0.1:8080`， 则 `http://127.0.0.1:8080/${PREFIX}`（默认为 'http://127.0.0.1:8080/docs'） 地址访问所有 `A4 Docs` Home 页面。\n */\n",
              "excerptTokens": [
                {
                  "kind": "Content",
                  "text": "readonly prefix: "
                },
                {
                  "kind": "Content",
                  "text": "string"
                },
                {
                  "kind": "Content",
                  "text": ";"
                }
              ],
              "isReadonly": true,
              "isOptional": false,
              "releaseTag": "Public",
              "name": "prefix",
              "propertyTypeTokenRange": {
                "startIndex": 1,
                "endIndex": 2
              },
              "isStatic": false,
              "isProtected": false,
              "isAbstract": false
            },
            {
              "kind": "Property",
              "canonicalReference": "@hz-9/a4-docs!A4DocsModuleSchema#ui:member",
              "docComment": "",
              "excerptTokens": [
                {
                  "kind": "Content",
                  "text": "readonly ui: "
                },
                {
                  "kind": "Reference",
                  "text": "A4DocsUIModuleSchema",
                  "canonicalReference": "@hz-9/a4-docs!A4DocsUIModuleSchema:class"
                },
                {
                  "kind": "Content",
                  "text": ";"
                }
              ],
              "isReadonly": true,
              "isOptional": false,
              "releaseTag": "Public",
              "name": "ui",
              "propertyTypeTokenRange": {
                "startIndex": 1,
                "endIndex": 2
              },
              "isStatic": false,
              "isProtected": false,
              "isAbstract": false
            }
          ],
          "implementsTokenRanges": []
        },
        {
          "kind": "Class",
          "canonicalReference": "@hz-9/a4-docs!A4DocsModuleSchemaA:class",
          "docComment": "/**\n * `A4 Docs Module` 用于 Multi Schema 类型判断类\n *\n * @public\n */\n",
          "excerptTokens": [
            {
              "kind": "Content",
              "text": "export declare class A4DocsModuleSchemaA "
            }
          ],
          "fileUrlPath": "dist/schema/docs.schema.d.ts",
          "releaseTag": "Public",
          "isAbstract": false,
          "name": "A4DocsModuleSchemaA",
          "preserveMemberOrder": false,
          "members": [
            {
              "kind": "Property",
              "canonicalReference": "@hz-9/a4-docs!A4DocsModuleSchemaA#A4:member",
              "docComment": "",
              "excerptTokens": [
                {
                  "kind": "Content",
                  "text": "readonly A4: "
                },
                {
                  "kind": "Reference",
                  "text": "A4DocsModuleSchemaB",
                  "canonicalReference": "@hz-9/a4-docs!A4DocsModuleSchemaB:class"
                },
                {
                  "kind": "Content",
                  "text": ";"
                }
              ],
              "isReadonly": true,
              "isOptional": false,
              "releaseTag": "Public",
              "name": "A4",
              "propertyTypeTokenRange": {
                "startIndex": 1,
                "endIndex": 2
              },
              "isStatic": false,
              "isProtected": false,
              "isAbstract": false
            }
          ],
          "implementsTokenRanges": []
        },
        {
          "kind": "Class",
          "canonicalReference": "@hz-9/a4-docs!A4DocsModuleSchemaB:class",
          "docComment": "/**\n * `A4 Docs Module` 用于 Multi Schema 类型判断类（A4）\n *\n * @public\n */\n",
          "excerptTokens": [
            {
              "kind": "Content",
              "text": "export declare class A4DocsModuleSchemaB "
            }
          ],
          "fileUrlPath": "dist/schema/docs.schema.d.ts",
          "releaseTag": "Public",
          "isAbstract": false,
          "name": "A4DocsModuleSchemaB",
          "preserveMemberOrder": false,
          "members": [
            {
              "kind": "Property",
              "canonicalReference": "@hz-9/a4-docs!A4DocsModuleSchemaB#docs:member",
              "docComment": "",
              "excerptTokens": [
                {
                  "kind": "Content",
                  "text": "readonly docs: "
                },
                {
                  "kind": "Reference",
                  "text": "A4DocsModuleSchema",
                  "canonicalReference": "@hz-9/a4-docs!A4DocsModuleSchema:class"
                },
                {
                  "kind": "Content",
                  "text": ";"
                }
              ],
              "isReadonly": true,
              "isOptional": false,
              "releaseTag": "Public",
              "name": "docs",
              "propertyTypeTokenRange": {
                "startIndex": 1,
                "endIndex": 2
              },
              "isStatic": false,
              "isProtected": false,
              "isAbstract": false
            }
          ],
          "implementsTokenRanges": []
        },
        {
          "kind": "Class",
          "canonicalReference": "@hz-9/a4-docs!A4DocsUIModuleSchema:class",
          "docComment": "/**\n * `A4 Docs Module` 的配置项结构。(.ui)\n *\n * @public\n */\n",
          "excerptTokens": [
            {
              "kind": "Content",
              "text": "export declare class A4DocsUIModuleSchema "
            }
          ],
          "fileUrlPath": "dist/schema/docs.schema.d.ts",
          "releaseTag": "Public",
          "isAbstract": false,
          "name": "A4DocsUIModuleSchema",
          "preserveMemberOrder": false,
          "members": [
            {
              "kind": "Property",
              "canonicalReference": "@hz-9/a4-docs!A4DocsUIModuleSchema#open:member",
              "docComment": "/**\n * 是否显示 `Swagger` 在线文档。\n *\n * 作为 `ConfitSchema` 时，若缺省，则赋值为 [DOCS_MODULE_DEFAULT.UI.OPEN]\n */\n",
              "excerptTokens": [
                {
                  "kind": "Content",
                  "text": "readonly open: "
                },
                {
                  "kind": "Content",
                  "text": "boolean"
                },
                {
                  "kind": "Content",
                  "text": ";"
                }
              ],
              "isReadonly": true,
              "isOptional": false,
              "releaseTag": "Public",
              "name": "open",
              "propertyTypeTokenRange": {
                "startIndex": 1,
                "endIndex": 2
              },
              "isStatic": false,
              "isProtected": false,
              "isAbstract": false
            },
            {
              "kind": "Property",
              "canonicalReference": "@hz-9/a4-docs!A4DocsUIModuleSchema#path:member",
              "docComment": "/**\n * `Swagger` 在线文档的访问路径。\n *\n * 作为 `ConfitSchema` 时，若缺省，则赋值为 [DOCS_MODULE_DEFAULT.UI.PATH]\n *\n * 若服务启动地址为 `http://127.0.0.1:8080`， 则 `http://127.0.0.1:8080/${PREFIX}/${PATH}`（默认为 'http://127.0.0.1:8080/docs/swagger-ui'） 地址访问所有 `Swagger` 在线文档。\n */\n",
              "excerptTokens": [
                {
                  "kind": "Content",
                  "text": "readonly path: "
                },
                {
                  "kind": "Content",
                  "text": "string"
                },
                {
                  "kind": "Content",
                  "text": ";"
                }
              ],
              "isReadonly": true,
              "isOptional": false,
              "releaseTag": "Public",
              "name": "path",
              "propertyTypeTokenRange": {
                "startIndex": 1,
                "endIndex": 2
              },
              "isStatic": false,
              "isProtected": false,
              "isAbstract": false
            }
          ],
          "implementsTokenRanges": []
        },
        {
          "kind": "Variable",
          "canonicalReference": "@hz-9/a4-docs!DOCS_MODULE_DEFAULT:var",
          "docComment": "/**\n * `A4 Docs` 配置信息(.swagger)默认值。\n *\n * 各参数说明，请查看\n *\n * @see\n *\n * SwaggerDocsConfigSchema\n *\n * @public\n */\n",
          "excerptTokens": [
            {
              "kind": "Content",
              "text": "DOCS_MODULE_DEFAULT: "
            },
            {
              "kind": "Content",
              "text": "{\n    readonly PREFIX: \"docs\";\n    readonly UI: {\n        readonly OPEN: true;\n        readonly PATH: \"openapi-ui\";\n    };\n    readonly SINGLE_FILE: {\n        readonly OPEN: true;\n        readonly EXPORT: true;\n        readonly FILEDIR: \"docs/api\";\n        readonly FILENAME: \"openapi.json\";\n    };\n    readonly MICRO_SERVICE_FILE: {\n        readonly OPEN: false;\n        readonly EXPORT: false;\n        readonly FILEDIR: \"docs/api\";\n        readonly FILENAME: \"micro-service.openapi.json\";\n    };\n}"
            }
          ],
          "fileUrlPath": "dist/const/index.d.ts",
          "isReadonly": true,
          "releaseTag": "Public",
          "name": "DOCS_MODULE_DEFAULT",
          "variableTypeTokenRange": {
            "startIndex": 1,
            "endIndex": 2
          }
        },
        {
          "kind": "Interface",
          "canonicalReference": "@hz-9/a4-docs!IDocsConstructorOptions:interface",
          "docComment": "/**\n * A4Docs 构造函数参数\n *\n * @public\n */\n",
          "excerptTokens": [
            {
              "kind": "Content",
              "text": "export interface IDocsConstructorOptions extends "
            },
            {
              "kind": "Reference",
              "text": "IDocsInfo",
              "canonicalReference": "@hz-9/a4-docs!IDocsInfo:interface"
            },
            {
              "kind": "Content",
              "text": " "
            }
          ],
          "fileUrlPath": "dist/interface/docs.d.ts",
          "releaseTag": "Public",
          "name": "IDocsConstructorOptions",
          "preserveMemberOrder": false,
          "members": [],
          "extendsTokenRanges": [
            {
              "startIndex": 1,
              "endIndex": 2
            }
          ]
        },
        {
          "kind": "Interface",
          "canonicalReference": "@hz-9/a4-docs!IDocsInfo:interface",
          "docComment": "/**\n * `DocsModule` 在运行时，需要的数据结构。\n *\n * @public\n */\n",
          "excerptTokens": [
            {
              "kind": "Content",
              "text": "export interface IDocsInfo extends "
            },
            {
              "kind": "Reference",
              "text": "A4DocsModuleSchema",
              "canonicalReference": "@hz-9/a4-docs!A4DocsModuleSchema:class"
            },
            {
              "kind": "Content",
              "text": " "
            }
          ],
          "fileUrlPath": "dist/interface/docs.d.ts",
          "releaseTag": "Public",
          "name": "IDocsInfo",
          "preserveMemberOrder": false,
          "members": [
            {
              "kind": "PropertySignature",
              "canonicalReference": "@hz-9/a4-docs!IDocsInfo#pathInfo:member",
              "docComment": "",
              "excerptTokens": [
                {
                  "kind": "Content",
                  "text": "pathInfo: "
                },
                {
                  "kind": "Reference",
                  "text": "IA4PathInfo",
                  "canonicalReference": "@hz-9/a4-core!IA4PathInfo:interface"
                },
                {
                  "kind": "Content",
                  "text": ";"
                }
              ],
              "isReadonly": false,
              "isOptional": false,
              "releaseTag": "Public",
              "name": "pathInfo",
              "propertyTypeTokenRange": {
                "startIndex": 1,
                "endIndex": 2
              }
            },
            {
              "kind": "PropertySignature",
              "canonicalReference": "@hz-9/a4-docs!IDocsInfo#statsInfo:member",
              "docComment": "",
              "excerptTokens": [
                {
                  "kind": "Content",
                  "text": "statsInfo: "
                },
                {
                  "kind": "Reference",
                  "text": "IA4StatusInfo",
                  "canonicalReference": "@hz-9/a4-core!IA4StatusInfo:interface"
                },
                {
                  "kind": "Content",
                  "text": ";"
                }
              ],
              "isReadonly": false,
              "isOptional": false,
              "releaseTag": "Public",
              "name": "statsInfo",
              "propertyTypeTokenRange": {
                "startIndex": 1,
                "endIndex": 2
              }
            }
          ],
          "extendsTokenRanges": [
            {
              "startIndex": 1,
              "endIndex": 2
            }
          ]
        }
      ]
    }
  ]
}
